pygeoapi/__init__.py
pygeoapi/config.py
pygeoapi/crs.py
pygeoapi/django_app.py
pygeoapi/error.py
pygeoapi/flask_app.py
pygeoapi/l10n.py
pygeoapi/linked_data.py
pygeoapi/log.py
pygeoapi/openapi.py
pygeoapi/plugin.py
pygeoapi/starlette_app.py
pygeoapi/util.py
pygeoapi/api/__init__.py
pygeoapi/api/admin.py
pygeoapi/api/coverages.py
pygeoapi/api/environmental_data_retrieval.py
pygeoapi/api/itemtypes.py
pygeoapi/api/maps.py
pygeoapi/api/processes.py
pygeoapi/api/stac.py
pygeoapi/api/tiles.py
pygeoapi/django_/__init__.py
pygeoapi/django_/settings.py
pygeoapi/django_/urls.py
pygeoapi/django_/views.py
pygeoapi/django_/wsgi.py
pygeoapi/formatter/__init__.py
pygeoapi/formatter/base.py
pygeoapi/formatter/csv_.py
pygeoapi/models/__init__.py
pygeoapi/models/config.py
pygeoapi/models/openapi.py
pygeoapi/models/provider/__init__.py
pygeoapi/models/provider/base.py
pygeoapi/models/provider/mvt.py
pygeoapi/process/__init__.py
pygeoapi/process/base.py
pygeoapi/process/echo.py
pygeoapi/process/hello_world.py
pygeoapi/process/shapely_functions.py
pygeoapi/process/manager/__init__.py
pygeoapi/process/manager/base.py
pygeoapi/process/manager/dummy.py
pygeoapi/process/manager/mongodb_.py
pygeoapi/process/manager/postgresql.py
pygeoapi/process/manager/tinydb_.py
pygeoapi/provider/__init__.py
pygeoapi/provider/azure_.py
pygeoapi/provider/base.py
pygeoapi/provider/base_edr.py
pygeoapi/provider/base_mvt.py
pygeoapi/provider/csv_.py
pygeoapi/provider/csw_facade.py
pygeoapi/provider/elasticsearch_.py
pygeoapi/provider/erddap.py
pygeoapi/provider/esri.py
pygeoapi/provider/filesystem.py
pygeoapi/provider/geojson.py
pygeoapi/provider/hateoas.py
pygeoapi/provider/mapscript_.py
pygeoapi/provider/mongo.py
pygeoapi/provider/mvt_elastic.py
pygeoapi/provider/mvt_postgresql.py
pygeoapi/provider/mvt_proxy.py
pygeoapi/provider/mvt_tippecanoe.py
pygeoapi/provider/ogr.py
pygeoapi/provider/opensearch_.py
pygeoapi/provider/oracle.py
pygeoapi/provider/parquet.py
pygeoapi/provider/rasterio_.py
pygeoapi-0.22.0.dist-info/licenses/LICENSE.md
pygeoapi-0.22.0.dist-info/METADATA
pygeoapi-0.22.0.dist-info/WHEEL
pygeoapi-0.22.0.dist-info/entry_points.txt
pygeoapi-0.22.0.dist-info/top_level.txt
pygeoapi-0.22.0.dist-info/RECORD
