Metadata-Version: 2.4
Name: pygeoapi
Version: 0.22.0
Summary: pygeoapi provides an API to geospatial data
Home-page: https://pygeoapi.io
Author: Tom Kralidis
Author-email: tomkralidis@gmail.com
Maintainer: Tom Kralidis
Maintainer-email: tomkralidis@gmail.com
License: MIT
Keywords: geospatial data api
Platform: all
Classifier: Development Status :: 5 - Production/Stable
Classifier: Environment :: Console
Classifier: Intended Audience :: Developers
Classifier: Intended Audience :: Science/Research
Classifier: License :: OSI Approved :: MIT License
Classifier: Operating System :: OS Independent
Classifier: Programming Language :: Python
Classifier: Topic :: Scientific/Engineering :: GIS
Requires-Python: >=3.12
License-File: LICENSE.md
Requires-Dist: Babel
Requires-Dist: click
Requires-Dist: filelock
Requires-Dist: Flask
Requires-Dist: jinja2
Requires-Dist: jsonschema
Requires-Dist: pydantic
Requires-Dist: pygeofilter
Requires-Dist: pygeoif
Requires-Dist: pyproj
Requires-Dist: python-dateutil
Requires-Dist: pytz
Requires-Dist: PyYAML
Requires-Dist: rasterio
Requires-Dist: requests
Requires-Dist: shapely
Requires-Dist: SQLAlchemy
Requires-Dist: tinydb
Dynamic: author
Dynamic: author-email
Dynamic: classifier
Dynamic: description
Dynamic: description-content-type
Dynamic: home-page
Dynamic: keywords
Dynamic: license
Dynamic: license-file
Dynamic: maintainer
Dynamic: maintainer-email
Dynamic: platform
Dynamic: requires-dist
Dynamic: requires-python
Dynamic: summary
